configcollector/__init__.py
configcollector/configcollector.py
configcollector/router.py
configcollector-0.1.1.dist-info/DESCRIPTION.rst
configcollector-0.1.1.dist-info/entry_points.txt
configcollector-0.1.1.dist-info/METADATA
configcollector-0.1.1.dist-info/metadata.json
configcollector-0.1.1.dist-info/RECORD
configcollector-0.1.1.dist-info/top_level.txt
configcollector-0.1.1.dist-info/WHEEL
