Metadata-Version: 2.0
Name: configcollector
Version: 0.1.1
Summary: The tool collects configuration file of multiple routers
Home-page: UNKNOWN
Author: Taiji Tsuchiya
Author-email: tuty0630@gmail.com
License: MIT
Keywords: network router cisco juniper junos ios ios-xr ios-xe
Platform: UNKNOWN
Requires-Dist: Exscript
